{
  "sections": {
    "main": {
      "type": "main-page",
      "custom_css": [
        "h3 {text-align: center;}"
      ],
      "settings": {
      }
    },
    "a418db7d-6add-4d39-9aea-f681c1803445": {
      "type": "custom-liquid",
      "custom_css": [

      ],
      "settings": {
        "custom_liquid": "<iframe src=\"https:\/\/calendar.google.com\/calendar\/embed?height=900&amp;wkst=1&amp;bgcolor=%23ffffff&amp;ctz=America%2FLos_Angeles&amp;src=Y19ncDZuYjVsYm81ZDNsbDZsdjRxM3ExOGR1a0Bncm91cC5jYWxlbmRhci5nb29nbGUuY29t&amp;src=bGF2YXBvcndob2xlc2FsZS5jb21fNDQ3dTlmbnJmdXA5M2RsZ2l0N29yNXFqaDBAZ3JvdXAuY2FsZW5kYXIuZ29vZ2xlLmNvbQ&amp;src=bGF2YXBvcndob2xlc2FsZS5jb21fbnJpOGw0dWsxMWZuYTZiM3YycW0zbmk4ZzRAZ3JvdXAuY2FsZW5kYXIuZ29vZ2xlLmNvbQ&amp;color=%233F51B5&amp;color=%23F6BF26&amp;color=%2333B679&amp;showTitle=0&amp;showNav=0&amp;showDate=0&amp;showPrint=0&amp;showTabs=0&amp;showCalendars=0&amp;showTz=0\" style=\"border-width:0\" width=\"100%\" height=\"900\" frameborder=\"0\" scrolling=\"no\"><\/iframe>"
      }
    },
    "e8cd25d6-25bd-4473-9fd2-c9c852ffdd23": {
      "type": "custom-liquid",
      "settings": {
        "custom_liquid": "<style><!--\n.row1 {\n\n.column {\n    flex: 50%;\n}\n}\n.column11 {flex: 50%;\n}\n--><\/style>\n<!--BLACK LINE-->\n<div style=\"padding-left: 16px; border-bottom: 5px solid black;\" class=\"column\"><\/div>\n<br \/><br \/> <!--BLACK LINE--> <!--DATE--> <span style=\"font-weight: bold; font-size: 30px; text-transform: uppercase;\">Friday March 17th<\/span> <br \/> <!--PRODUCT-->\n<div style=\"font-weight: bold; padding-left: 20px;\"><span style=\"font-weight: 200; font-size: 30px; text-transform: uppercase;\"> <b> <!--Brand--> CANDY KING <!--End of Brand--> <\/b> <\/span>\n<div style=\"padding-left: 20px; line-height: 25px;\"><span style=\"font-size: 18px;\"><a href=\"https:\/\/www.lavaporwholesale.com\/products\/candy-king-100ml\" style=\"color: #0059b3;\"> <!--Name--> 100mL Candy King <!--End of Name--> <\/a> <br \/>        <br \/><\/span> <span style=\"font-size: 18px;\"><a href=\"https:\/\/www.lavaporwholesale.com\/products\/candy-king-salt-30ml-1\" style=\"color: #0059b3;\"> <!--Name--> 30mL Candy King SALT <!--End of Name--> <\/a> <br \/>        <br \/><\/span> <span style=\"font-size: 18px;\"><a href=\"https:\/\/www.lavaporwholesale.com\/products\/candy-king-100ml-1\" style=\"color: #0059b3;\"> <!--Name--> CA - 100mL Candy King <!--End of Name--> <\/a> <br \/>        <br \/><\/span> <span style=\"font-size: 18px;\"><a href=\"https:\/\/www.lavaporwholesale.com\/products\/candy-king-salt-30ml\" style=\"color: #0059b3;\"> <!--Name--> CA - 30mL Candy King SALT <!--End of Name--> <\/a> <br \/>        <br \/><\/span><\/div>\n<\/div>\n<br \/><br \/> <!--END OF PRODUCT--> <!--PRODUCT-->\n<div style=\"font-weight: bold; padding-left: 20px;\"><span style=\"font-weight: 200; font-size: 30px; text-transform: uppercase;\"> <b> <!--Brand--> COASTAL CLOUDS <!--End of Brand--> <\/b> <\/span>\n<div style=\"padding-left: 20px; line-height: 25px;\"><span style=\"font-size: 18px;\"><a href=\"https:\/\/www.lavaporwholesale.com\/products\/coastal-clouds-salt-30ml\" style=\"color: #0059b3;\"> <!--Name--> CA -30mL Coastal Clouds SALT <!--End of Name--> <\/a> <br \/>        <br \/><\/span> <span style=\"font-size: 18px;\"><a href=\"https:\/\/www.lavaporwholesale.com\/products\/coastal-clouds-60ml\" style=\"color: #0059b3;\"> <!--Name--> CA -60mL Coastal Clouds <!--End of Name--> <\/a> <br \/>        <br \/><\/span><\/div>\n<\/div>\n<br \/><br \/> <!--END OF PRODUCT--> <!--PRODUCT-->\n<div style=\"font-weight: bold; padding-left: 20px;\"><span style=\"font-weight: 200; font-size: 30px; text-transform: uppercase;\"> <b> <!--Brand--> EARTH WELLNESS <!--End of Brand--> <\/b> <\/span>\n<div style=\"padding-left: 20px; line-height: 25px;\"><span style=\"font-size: 18px;\"><a href=\"https:\/\/www.lavaporwholesale.com\/products\/earth-wellness-full-spectrum-cbd-gummies-30ct-dropship\" style=\"color: #0059b3;\"> <!--Name--> Earth Wellness Full Spectrum CBD Gummies 30ct [DROPSHIP] <!--End of Name--> <\/a> <br \/>        <br \/><\/span> <span style=\"font-size: 18px;\"><a href=\"https:\/\/www.lavaporwholesale.com\/products\/earth-wellness-thc-free-cbd-gummies-30ct-dropship\" style=\"color: #0059b3;\"> <!--Name--> Earth Wellness THC Free CBD Gummies 30ct [DROPSHIP] <!--End of Name--> <\/a> <br \/>        <br \/><\/span> <span style=\"font-size: 18px;\"><a href=\"https:\/\/www.lavaporwholesale.com\/products\/earth-wellness-thc-gummies-30ct-1-pack-dropship\" style=\"color: #0059b3;\"> <!--Name--> Earth Wellness THC Gummies 30ct [DROPSHIP] <!--End of Name--> <\/a> <br \/>        <br \/><\/span> <span style=\"font-size: 18px;\"><a href=\"https:\/\/www.lavaporwholesale.com\/products\/earth-wellness-cbd-tincture-3-7ml-6-pack-dropship\" style=\"color: #0059b3;\"> <!--Name--> Earth Wellness CBD Tincture 3.7mL (6\/Pack) [DROPSHIP] <!--End of Name--> <\/a> <br \/>        <br \/><\/span> <span style=\"font-size: 18px;\"><a href=\"https:\/\/www.lavaporwholesale.com\/products\/earth-wellness-cbd-tincture-30ml-6-pack-dropship\" style=\"color: #0059b3;\"> <!--Name--> Earth Wellness CBD Tincture 30mL (6\/Pack) [DROPSHIP] <!--End of Name--> <\/a> <br \/>        <br \/><\/span> <span style=\"font-size: 18px;\"><a href=\"https:\/\/www.lavaporwholesale.com\/products\/earth-wellness-cbd-thc-tincture-3-7ml-6-pack-dropship\" style=\"color: #0059b3;\"> <!--Name--> Earth Wellness CBD THC Tincture 3.7mL (6\/Pack) [DROPSHIP] <!--End of Name--> <\/a> <br \/>        <br \/><\/span> <span style=\"font-size: 18px;\"><a href=\"https:\/\/www.lavaporwholesale.com\/products\/earth-wellness-cbd-vape-juice-30ml-6-pack-dropship\" style=\"color: #0059b3;\"> <!--Name--> Earth Wellness CBD Vape Juice 30mL (6\/Pack) [DROPSHIP] <!--End of Name--> <\/a> <br \/>        <br \/><\/span> <span style=\"font-size: 18px;\"><a href=\"https:\/\/www.lavaporwholesale.com\/products\/earth-wellness-cbd-vape-juice-3-7ml-dropship\" style=\"color: #0059b3;\"> <!--Name--> Earth Wellness CBD Vape Juice 3.7mL [DROPSHIP] <!--End of Name--> <\/a> <br \/>        <br \/><\/span><\/div>\n<\/div>\n<br \/><br \/> <!--END OF PRODUCT--> <!--PRODUCT-->\n<div style=\"font-weight: bold; padding-left: 20px;\"><span style=\"font-weight: 200; font-size: 30px; text-transform: uppercase;\"> <b> <!--Brand--> EB DESIGN <!--End of Brand--> <\/b> <\/span>\n<div style=\"padding-left: 20px; line-height: 25px;\"><span style=\"font-size: 18px;\"><a href=\"https:\/\/www.lavaporwholesale.com\/products\/eb-design-airo-max-5000-disposable-13ml-10-pack\" style=\"color: #0059b3;\"> <!--Name--> EB Design Airo Max 5000 Disposable 13mL (10\/Pack) <!--End of Name--> <\/a> <br \/>        <br \/><\/span> <span style=\"font-size: 18px;\"><a href=\"https:\/\/www.lavaporwholesale.com\/products\/eb-design-funky-republic-ti7000-disposable-17ml-pack-5\" style=\"color: #0059b3;\"> <!--Name--> EB Design Funky Republic Ti7000 Disposable 17mL <!--End of Name--> <\/a> <br \/>        <br \/><\/span><\/div>\n<\/div>\n<br \/><br \/> <!--END OF PRODUCT--> <!--PRODUCT-->\n<div style=\"font-weight: bold; padding-left: 20px;\"><span style=\"font-weight: 200; font-size: 30px; text-transform: uppercase;\"> <b> <!--Brand--> EZZY <!--End of Brand--> <\/b> <\/span>\n<div style=\"padding-left: 20px; line-height: 25px;\"><span style=\"font-size: 18px;\"><a href=\"https:\/\/www.lavaporwholesale.com\/products\/ezzy-air-disposables-2-7ml-10-pack-dropship\" style=\"color: #0059b3;\"> <!--Name--> Ezzy Air Disposables 2.7mL (10\/Pack) [DROPSHIP] <!--End of Name--> <\/a> <br \/>        <br \/><\/span><\/div>\n<\/div>\n<br \/><br \/> <!--END OF PRODUCT--> <!--PRODUCT-->\n<div style=\"font-weight: bold; padding-left: 20px;\"><span style=\"font-weight: 200; font-size: 30px; text-transform: uppercase;\"> <b> <!--Brand--> GOOD VIBEZ <!--End of Brand--> <\/b> <\/span>\n<div style=\"padding-left: 20px; line-height: 25px;\"><span style=\"font-size: 18px;\"><a href=\"https:\/\/www.lavaporwholesale.com\/products\/good-vibez-delta-8-oral-strips-10ct-250mg-12-pack-dropship\" style=\"color: #0059b3;\"> <!--Name--> Good Vibez Delta 8 Oral Strips 10ct 250mg (12\/Pack) [DROPSHIP] <!--End of Name--> <\/a> <br \/>        <br \/><\/span><\/div>\n<\/div>\n<br \/><br \/> <!--END OF PRODUCT--> <!--PRODUCT-->\n<div style=\"font-weight: bold; padding-left: 20px;\"><span style=\"font-weight: 200; font-size: 30px; text-transform: uppercase;\"> <b> <!--Brand--> JUICE HEAD <!--End of Brand--> <\/b> <\/span>\n<div style=\"padding-left: 20px; line-height: 25px;\"><span style=\"font-size: 18px;\"><a href=\"https:\/\/www.lavaporwholesale.com\/products\/juice-head-desserts-100ml\" style=\"color: #0059b3;\"> <!--Name--> CA - 100mL Juice Head Desserts <!--End of Name--> <\/a> <br \/>        <br \/><\/span> <span style=\"font-size: 18px;\"><a href=\"https:\/\/www.lavaporwholesale.com\/products\/juice-head-100ml\" style=\"color: #0059b3;\"> <!--Name--> CA -100mL Juice Head <!--End of Name--> <\/a> <br \/>        <br \/><\/span> <span style=\"font-size: 18px;\"><a href=\"https:\/\/www.lavaporwholesale.com\/products\/juice-head-freeze-100ml\" style=\"color: #0059b3;\"> <!--Name--> CA -100mL Juice Head FREEZE <!--End of Name--> <\/a> <br \/>        <br \/><\/span> <span style=\"font-size: 18px;\"><a href=\"https:\/\/www.lavaporwholesale.com\/products\/juice-head-salt-30ml\" style=\"color: #0059b3;\"> <!--Name--> CA -30mL Juice Head SALT <!--End of Name--> <\/a> <br \/>        <br \/><\/span><\/div>\n<\/div>\n<br \/><br \/> <!--END OF PRODUCT--> <!--PRODUCT-->\n<div style=\"font-weight: bold; padding-left: 20px;\"><span style=\"font-weight: 200; font-size: 30px; text-transform: uppercase;\"> <b> <!--Brand--> NAKED <!--End of Brand--> <\/b> <\/span>\n<div style=\"padding-left: 20px; line-height: 25px;\"><span style=\"font-size: 18px;\"><a href=\"https:\/\/www.lavaporwholesale.com\/products\/naked100-salt-30ml\" style=\"color: #0059b3;\"> <!--Name--> CA -30mL Naked100 SALT <!--End of Name--> <\/a> <br \/>        <br \/><\/span> <span style=\"font-size: 18px;\"><a href=\"https:\/\/www.lavaporwholesale.com\/products\/naked-100-60ml\" style=\"color: #0059b3;\"> <!--Name--> CA -60mL Naked100 <!--End of Name--> <\/a> <br \/>        <br \/><\/span><\/div>\n<\/div>\n<br \/><br \/> <!--END OF PRODUCT--><!--PRODUCT-->\n<div style=\"font-weight: bold; padding-left: 20px;\"><span style=\"font-weight: 200; font-size: 30px; text-transform: uppercase;\"> <b> <!--Brand--> SO SOUL <!--End of Brand--> <\/b> <\/span>\n<div style=\"padding-left: 20px; line-height: 25px;\"><span style=\"font-size: 18px;\"><a href=\"https:\/\/www.lavaporwholesale.com\/products\/so-soul-slimz-bc5000-pro-disposable-11ml-10-pack-1\" style=\"color: #0059b3;\"> <!--Name--> CA - 110mL So Soul SLIMZ BC 5000 Pro Disposable <!--End of Name--> <\/a> <br \/>        <br \/><\/span><\/div>\n<\/div>\n<br \/><br \/> <!--END OF PRODUCT--> <!--PRODUCT-->\n<div style=\"font-weight: bold; padding-left: 20px;\"><span style=\"font-weight: 200; font-size: 30px; text-transform: uppercase;\"> <b> <!--Brand--> TWO HAWK <!--End of Brand--> <\/b> <\/span>\n<div style=\"padding-left: 20px; line-height: 25px;\"><span style=\"font-size: 18px;\"><a href=\"https:\/\/www.lavaporwholesale.com\/products\/two-hawk-storyteller-delta-8-gummy-20ct-6-pack-dropship\" style=\"color: #0059b3;\"> <!--Name--> Two Hawk Storyteller Delta 8 Gummy 20ct (6\/Pack) [DROPSHIP] <!--End of Name--> <\/a> <br \/>        <br \/><\/span> <span style=\"font-size: 18px;\"><a href=\"https:\/\/www.lavaporwholesale.com\/products\/two-hawk-dreamcatcher-delta-8-gummy-20ct-6-pack-dropship\" style=\"color: #0059b3;\"> <!--Name--> Two Hawk Dreamcatcher Delta 8 Gummy 20ct (6\/Pack) [DROPSHIP] <!--End of Name--> <\/a> <br \/>        <br \/><\/span> <span style=\"font-size: 18px;\"><a href=\"https:\/\/www.lavaporwholesale.com\/products\/two-hawk-warrior-delta-8-gummy-20ct-6-pack-dropship\" style=\"color: #0059b3;\"> <!--Name--> Two Hawk Warrior Delta 8 Gummy 20ct (6\/Pack) [DROPSHIP] <!--End of Name--> <\/a> <br \/>        <br \/><\/span> <span style=\"font-size: 18px;\"><a href=\"https:\/\/www.lavaporwholesale.com\/products\/two-hawk-delta-9-gummy-20ct-6-pack-dropship\" style=\"color: #0059b3;\"> <!--Name--> Two Hawk Delta 9 Gummy 20ct (6\/Pack) [DROPSHIP] <!--End of Name--> <\/a> <br \/>        <br \/><\/span> <span style=\"font-size: 18px;\"><a href=\"https:\/\/www.lavaporwholesale.com\/products\/two-hawk-hhc-gummy-20ct-6-pack-dropship\" style=\"color: #0059b3;\"> <!--Name--> Two Hawk HHC Gummy 20ct (6\/Pack) [DROPSHIP] <!--End of Name--> <\/a> <br \/>        <br \/><\/span> <span style=\"font-size: 18px;\"><a href=\"https:\/\/www.lavaporwholesale.com\/products\/two-hawk-delta-8-tincture-3-7ml-dropship\" style=\"color: #0059b3;\"> <!--Name--> Two Hawk Delta 8 Tincture 3.7mL [DROPSHIP] <!--End of Name--> <\/a> <br \/>        <br \/><\/span> <span style=\"font-size: 18px;\"><a href=\"https:\/\/www.lavaporwholesale.com\/products\/two-hawk-delta-8-tincture-30ml-dropship\" style=\"color: #0059b3;\"> <!--Name--> Two Hawk Delta 8 Tincture 30mL [DROPSHIP] <!--End of Name--> <\/a> <br \/>        <br \/><\/span> <span style=\"font-size: 18px;\"><a href=\"https:\/\/www.lavaporwholesale.com\/products\/two-hawk-delta-8-disposable-2g-5-pack-dropship\" style=\"color: #0059b3;\"> <!--Name--> Two Hawk Delta 8 Disposable 2g (5\/Pack) [DROPSHIP] <!--End of Name--> <\/a> <br \/>        <br \/><\/span> <span style=\"font-size: 18px;\"><a href=\"https:\/\/www.lavaporwholesale.com\/products\/two-hawk-delta-8-cartridge-2g-dropship\" style=\"color: #0059b3;\"> <!--Name--> Two Hawk Delta 8 Cartridge 2g [DROPSHIP] <!--End of Name--> <\/a> <br \/>        <br \/><\/span><\/div>\n<\/div>\n<br \/><br \/> <!--END OF PRODUCT--> <!--PRODUCT-->\n<div style=\"font-weight: bold; padding-left: 20px;\"><span style=\"font-weight: 200; font-size: 30px; text-transform: uppercase;\"> <b> <!--Brand--> VAPORESSO <!--End of Brand--> <\/b> <\/span>\n<div style=\"padding-left: 20px; line-height: 25px;\"><span style=\"font-size: 18px;\"><a href=\"https:\/\/www.lavaporwholesale.com\/products\/vaporesso-luxe-x-replacement-pods\" style=\"color: #0059b3;\"> <!--Name--> Vaporesso Luxe X Pod 0.4ohm (2\/Pack) <!--End of Name--> <\/a> <br \/>        <br \/><\/span> <span style=\"font-size: 18px;\"><a href=\"https:\/\/www.lavaporwholesale.com\/products\/vaporesso-luxe-xr-40w-pod-system-kit-1500mah\" style=\"color: #0059b3;\"> <!--Name--> Vaporesso Luxe XR Kit <!--End of Name--> <\/a> <br \/>        <br \/><\/span><\/div>\n<\/div>\n<br \/><br \/> <!--END OF PRODUCT--> <!--BLACK LINE-->\n<div style=\"padding-left: 16px; border-bottom: 5px solid black;\" class=\"column\"><\/div>\n<br \/><br \/> <!--BLACK LINE--> <!--DATE--> <span style=\"font-weight: bold; font-size: 30px; text-transform: uppercase;\">Wednesday March 15th<\/span> <br \/> <!--PRODUCT-->\n<div style=\"font-weight: bold; padding-left: 20px;\"><span style=\"font-weight: 200; font-size: 30px; text-transform: uppercase;\"> <b> <!--Brand--> BIFF BAR <!--End of Brand--> <\/b> <\/span>\n<div style=\"padding-left: 20px; line-height: 25px;\"><span style=\"font-size: 18px;\"><a href=\"https:\/\/www.lavaporwholesale.com\/products\/biff-bar-lux-5500-disposable-13ml-10-pack\" style=\"color: #0059b3;\"> <!--Name--> Biff Bar Lux 5500 Disposable 13mL (10\/Pack) <!--End of Name--> <\/a> <br \/>        <br \/><\/span><\/div>\n<\/div>\n<br \/><br \/> <!--END OF PRODUCT--> <!--PRODUCT-->\n<div style=\"font-weight: bold; padding-left: 20px;\"><span style=\"font-weight: 200; font-size: 30px; text-transform: uppercase;\"> <b> <!--Brand--> GEEKVAPE <!--End of Brand--> <\/b> <\/span>\n<div style=\"padding-left: 20px; line-height: 25px;\"><span style=\"font-size: 18px;\"><a href=\"https:\/\/www.lavaporwholesale.com\/products\/geek-vape-aegis-boost-replacement-coils\" style=\"color: #0059b3;\"> <!--Name--> Geekvape B Series Coil (5\/pack) <!--End of Name--> <\/a> <br \/>        <br \/><\/span> <span style=\"font-size: 18px;\"><a href=\"https:\/\/www.lavaporwholesale.com\/products\/geek-vape-u-replacement-pods\" style=\"color: #0059b3;\"> <!--Name--> Geekvape U Replacement Pods (3\/pack) <!--End of Name--> <\/a> <br \/>        <br \/><\/span> <span style=\"font-size: 18px;\"><a href=\"https:\/\/www.lavaporwholesale.com\/products\/geek-vape-ka1-series-replacement-coils\" style=\"color: #0059b3;\"> <!--Name--> Geekvape Z Series Coil (5\/pack) <!--End of Name--> <\/a> <br \/>        <br \/><\/span><\/div>\n<\/div>\n<br \/><br \/> <!--END OF PRODUCT--> <!--PRODUCT-->\n<div style=\"font-weight: bold; padding-left: 20px;\"><span style=\"font-weight: 200; font-size: 30px; text-transform: uppercase;\"> <b> <!--Brand--> NAKED <!--End of Brand--> <\/b> <\/span>\n<div style=\"padding-left: 20px; line-height: 25px;\"><span style=\"font-size: 18px;\"><a href=\"https:\/\/www.lavaporwholesale.com\/products\/nkd-flavors-concentrate-30ml-10-pack\" style=\"color: #0059b3;\"> <!--Name--> NKD Multi-Purpose Flavors 30mL (10\/Pack) <!--End of Name--> <\/a> <br \/>        <br \/><\/span><\/div>\n<\/div>\n<br \/><br \/> <!--END OF PRODUCT--> <!--PRODUCT-->\n<div style=\"font-weight: bold; padding-left: 20px;\"><span style=\"font-weight: 200; font-size: 30px; text-transform: uppercase;\"> <b> <!--Brand--> NIC FILL <!--End of Brand--> <\/b> <\/span>\n<div style=\"padding-left: 20px; line-height: 25px;\"><span style=\"font-size: 18px;\"><a href=\"https:\/\/www.lavaporwholesale.com\/products\/nic-fill-nicotine-base-70ml-10-pack\" style=\"color: #0059b3;\"> <!--Name--> Nic Fill Nicotine Base 70mL (10\/Pack) <!--End of Name--> <\/a> <br \/>        <br \/><\/span><\/div>\n<\/div>\n<br \/><br \/> <!--END OF PRODUCT--> <!--BLACK LINE-->\n<div style=\"padding-left: 16px; border-bottom: 5px solid black;\" class=\"column\"><\/div>\n<br \/><br \/> <!--BLACK LINE--> <!--DATE--> <span style=\"font-weight: bold; font-size: 30px; text-transform: uppercase;\">Tuesday March 14th<\/span> <br \/> <!--PRODUCT-->\n<div style=\"font-weight: bold; padding-left: 20px;\"><span style=\"font-weight: 200; font-size: 30px; text-transform: uppercase;\"> <b> <!--Brand--> CHUBBY BUBBLE VAPES <!--End of Brand--> <\/b> <\/span>\n<div style=\"padding-left: 20px; line-height: 25px;\"><span style=\"font-size: 18px;\"><a href=\"https:\/\/www.lavaporwholesale.com\/products\/chubby-bubble-vapes-100ml-dropship\" style=\"color: #0059b3;\"> <!--Name--> CA - Chubby Bubble Vapes 100mL [DROPSHIP] <!--End of Name--> <\/a> <br \/>        <br \/><\/span> <span style=\"font-size: 18px;\"><a href=\"https:\/\/www.lavaporwholesale.com\/products\/chubby-bubble-vapes-100ml-dropship-1\" style=\"color: #0059b3;\"> <!--Name--> Chubby Bubble Vapes 100mL [DROPSHIP] <!--End of Name--> <\/a> <br \/>        <br \/><\/span> <span style=\"font-size: 18px;\"><a href=\"https:\/\/www.lavaporwholesale.com\/products\/hyve-x-chubby-bubble-vapes-disposable-12ml-5-pack-dropship\" style=\"color: #0059b3;\"> <!--Name--> HYVE x Chubby Bubble Vapes Disposable 12ml (5\/Pack) [DROPSHIP] <!--End of Name--> <\/a> <br \/>        <br \/><\/span> <span style=\"font-size: 18px;\"><a href=\"https:\/\/www.lavaporwholesale.com\/products\/hyve-x-chubby-bubble-vapes-disposable-10ml-5-pack-dropship\" style=\"color: #0059b3;\"> <!--Name--> HYVE x Chubby Bubble Vapes Disposable 10mL (5\/Pack) [DROPSHIP] <!--End of Name--> <\/a> <br \/>        <br \/><\/span> <span style=\"font-size: 18px;\"><a href=\"https:\/\/www.lavaporwholesale.com\/products\/hyve-x-chubby-bubble-vapes-disposable-10ml-10-pack-dropship\" style=\"color: #0059b3;\"> <!--Name--> HYVE x Chubby Bubble Vapes Disposable 10ml (10\/Pack) [DROPSHIP] <!--End of Name--> <\/a> <br \/>        <br \/><\/span><\/div>\n<\/div>\n<br \/><br \/> <!--END OF PRODUCT--> <!--PRODUCT-->\n<div style=\"font-weight: bold; padding-left: 20px;\"><span style=\"font-weight: 200; font-size: 30px; text-transform: uppercase;\"> <b> <!--Brand--> SO SOUL <!--End of Brand--> <\/b> <\/span>\n<div style=\"padding-left: 20px; line-height: 25px;\"><span style=\"font-size: 18px;\"><a href=\"https:\/\/www.lavaporwholesale.com\/products\/so-soul-slimz-bc5000-pro-disposable-11ml-10-pack\" style=\"color: #0059b3;\"> <!--Name--> 110mL So Soul SLIMZ BC 5000 Pro Disposable <!--End of Name--> <\/a> <br \/>        <br \/><\/span><\/div>\n<\/div>\n<br \/><br \/> <!--END OF PRODUCT--> <!--BLACK LINE-->\n<div style=\"padding-left: 16px; border-bottom: 5px solid black;\" class=\"column\"><\/div>\n<br \/><br \/> <!--BLACK LINE--> <!--DATE--> <span style=\"font-weight: bold; font-size: 30px; text-transform: uppercase;\">Monday March 13th<\/span> <br \/> <!--PRODUCT-->\n<div style=\"font-weight: bold; padding-left: 20px;\"><span style=\"font-weight: 200; font-size: 30px; text-transform: uppercase;\"> <b> <!--Brand--> EB DESIGN <!--End of Brand--> <\/b> <\/span>\n<div style=\"padding-left: 20px; line-height: 25px;\"><span style=\"font-size: 18px;\"><a href=\"https:\/\/www.lavaporwholesale.com\/products\/eb-design-lost-mary-mo5000-disposable-13ml-10-pack\" style=\"color: #0059b3;\"> <!--Name--> CA - EB Design 13mL Lost Mary MO5000 Disposable <!--End of Name--> <\/a> <br \/>        <br \/><\/span><\/div>\n<\/div>\n<br \/><br \/> <!--END OF PRODUCT--> <!--PRODUCT-->\n<div style=\"font-weight: bold; padding-left: 20px;\"><span style=\"font-weight: 200; font-size: 30px; text-transform: uppercase;\"> <b> <!--Brand--> MNKE <!--End of Brand--> <\/b> <\/span>\n<div style=\"padding-left: 20px; line-height: 25px;\"><span style=\"font-size: 18px;\"><a href=\"https:\/\/www.lavaporwholesale.com\/products\/mnke-bars-disposable-16ml-5-pack\" style=\"color: #0059b3;\"> <!--Name--> MNKE Bars Disposable 16mL (5\/Pack) <!--End of Name--> <\/a> <br \/>        <br \/><\/span><\/div>\n<\/div>\n<br \/><br \/> <!--END OF PRODUCT--> <!--PRODUCT-->\n<div style=\"font-weight: bold; padding-left: 20px;\"><span style=\"font-weight: 200; font-size: 30px; text-transform: uppercase;\"> <b> <!--Brand--> SMOK <!--End of Brand--> <\/b> <\/span>\n<div style=\"padding-left: 20px; line-height: 25px;\"><span style=\"font-size: 18px;\"><a href=\"https:\/\/www.lavaporwholesale.com\/products\/smok-lp2-replacement-coils\" style=\"color: #0059b3;\"> <!--Name--> LP2 Meshed 0.23ohm DL Coil (5\/pack) <!--End of Name--> <\/a> <br \/>        <br \/><\/span> <span style=\"font-size: 18px;\"><a href=\"https:\/\/www.lavaporwholesale.com\/products\/smok-nord-replacement-coils\" style=\"color: #0059b3;\"> <!--Name--> Nord Mesh Coil 0.6 ohm (5\/pack) <!--End of Name--> <\/a> <br \/>        <br \/><\/span> <span style=\"font-size: 18px;\"><a href=\"https:\/\/www.lavaporwholesale.com\/products\/smok-novo-2-replacement-pods-with-coils\" style=\"color: #0059b3;\"> <!--Name--> Novo 2 Pod (3\/pack) <!--End of Name--> <\/a> <br \/>        <br \/><\/span> <span style=\"font-size: 18px;\"><a href=\"https:\/\/www.lavaporwholesale.com\/products\/smok-novo-2x-mesh-mtl-replacement-pods\" style=\"color: #0059b3;\"> <!--Name--> Novo 2X Mesh MTL Pod 0.9ohm 2ml (3\/pack) <!--End of Name--> <\/a> <br \/>        <br \/><\/span> <span style=\"font-size: 18px;\"><a href=\"https:\/\/www.lavaporwholesale.com\/products\/smok-rpm-2-replacement-coils\" style=\"color: #0059b3;\"> <!--Name--> RPM2 Replacement Mesh Coil (5\/pack) \"RPM2\" <!--End of Name--> <\/a> <br \/>        <br \/><\/span> <span style=\"font-size: 18px;\"><a href=\"https:\/\/www.lavaporwholesale.com\/products\/smok-rpm-3-replacement-coils\" style=\"color: #0059b3;\"> <!--Name--> RPM3 Meshed Coil (5\/pack) <!--End of Name--> <\/a> <br \/>        <br \/><\/span> <span style=\"font-size: 18px;\"><a href=\"https:\/\/www.lavaporwholesale.com\/products\/smok-tfv16-mesh-coils\" style=\"color: #0059b3;\"> <!--Name--> TFV16 Coil - Mesh 0.17ohm (Not LITE) (3\/pack) <!--End of Name--> <\/a> <br \/>        <br \/><\/span><\/div>\n<\/div>\n<br \/><br \/> <!--END OF PRODUCT--> <!--PRODUCT-->\n<div style=\"font-weight: bold; padding-left: 20px;\"><span style=\"font-weight: 200; font-size: 30px; text-transform: uppercase;\"> <b> <!--Brand--> UWELL <!--End of Brand--> <\/b> <\/span>\n<div style=\"padding-left: 20px; line-height: 25px;\"><span style=\"font-size: 18px;\"><a href=\"https:\/\/www.lavaporwholesale.com\/products\/uwell-caliburn-a2-replacement-pods\" style=\"color: #0059b3;\"> <!--Name--> Caliburn A2 Refillable Pod 0.9ohm (4\/Pack) (2ml) <!--End of Name--> <\/a> <br \/>        <br \/><\/span> <span style=\"font-size: 18px;\"><a href=\"https:\/\/www.lavaporwholesale.com\/products\/uwell-caliburn-a3-replacement-pods\" style=\"color: #0059b3;\"> <!--Name--> Caliburn A3 Pod 1.0ohm (4\/pack) <!--End of Name--> <\/a> <br \/>        <br \/><\/span> <span style=\"font-size: 18px;\"><a href=\"https:\/\/www.lavaporwholesale.com\/products\/uwell-caliburn-g-replacement-pod\" style=\"color: #0059b3;\"> <!--Name--> Caliburn G Empty Pod (2\/pack) <!--End of Name--> <\/a> <br \/>        <br \/><\/span> <span style=\"font-size: 18px;\"><a href=\"https:\/\/www.lavaporwholesale.com\/products\/uwell-caliburn-g-replacement-coils\" style=\"color: #0059b3;\"> <!--Name--> Caliburn G Replacement Coil (4\/pack) <!--End of Name--> <\/a> <br \/>        <br \/><\/span> <span style=\"font-size: 18px;\"><a href=\"https:\/\/www.lavaporwholesale.com\/products\/uwell-caliburn-g2-empty-replacement-pods\" style=\"color: #0059b3;\"> <!--Name--> Caliburn G2 Empty Cartridge 2ml (2\/pack) <!--End of Name--> <\/a> <br \/>        <br \/><\/span> <span style=\"font-size: 18px;\"><a href=\"https:\/\/www.lavaporwholesale.com\/products\/uwell-caliburn-replacement-pods\" style=\"color: #0059b3;\"> <!--Name--> Caliburn Replacement Pod 1.4ohm (4\/pack) <!--End of Name--> <\/a> <br \/>        <br \/><\/span> <span style=\"font-size: 18px;\"><a href=\"https:\/\/www.lavaporwholesale.com\/products\/uwell-crown-v-replacement-coils\" style=\"color: #0059b3;\"> <!--Name--> Crown V UN2 Mesh Coil 0.23 ohm (4\/pack) <!--End of Name--> <\/a> <br \/>        <br \/><\/span> <span style=\"font-size: 18px;\"><a href=\"https:\/\/www.lavaporwholesale.com\/products\/uwell-popreel-p1-replacement-pods\" style=\"color: #0059b3;\"> <!--Name--> Popreel P1 Refillable Pod (4\/pack) <!--End of Name--> <\/a> <br \/>        <br \/><\/span> <span style=\"font-size: 18px;\"><a href=\"https:\/\/www.lavaporwholesale.com\/products\/uwell-un2-coils\" style=\"color: #0059b3;\"> <!--Name--> Valyrian 2 Coil UN2 Single Mesh 0.32ohm (2\/pack) <!--End of Name--> <\/a> <br \/>        <br \/><\/span><\/div>\n<\/div>\n<br \/><br \/> <!--END OF PRODUCT--> <!--BLACK LINE-->\n<div style=\"padding-left: 16px; border-bottom: 5px solid black;\" class=\"column\"><\/div>\n<br \/><br \/> <!--BLACK LINE-->"
      }
    }
  },
  "order": [
    "main",
    "a418db7d-6add-4d39-9aea-f681c1803445",
    "e8cd25d6-25bd-4473-9fd2-c9c852ffdd23"
  ]
}
